setup.py
rcpp/__init__.py
rcpp.egg-info/PKG-INFO
rcpp.egg-info/SOURCES.txt
rcpp.egg-info/dependency_links.txt
rcpp.egg-info/entry_points.txt
rcpp.egg-info/not-zip-safe
rcpp.egg-info/top_level.txt