Metadata-Version: 1.0
Name: rcpp
Version: 1.0
Summary: auto run cpp file
Home-page: UNKNOWN
Author: ahonn
Author-email: ahonn95@outlook.com
License: MIT License
Keywords: g++,cpp,cli,run
Platform: UNKNOWN
